[{"ID":1, "FIRST_NAME":"Libbi", "LAST_NAME":"Beardall", "AGE":53},
 {"ID":2, "FIRST_NAME":"Aubrie", "LAST_NAME":"Morland", "AGE":74},
 {"ID":3, "FIRST_NAME":"Godfrey", "LAST_NAME":"Mougenel", "AGE":52},
 {"ID":4, "FIRST_NAME":"Willi", "LAST_NAME":"Raun", "AGE":32},
 {"ID":5, "FIRST_NAME":"Torrie", "LAST_NAME":"Lamlin", "AGE":22},
 {"ID":6, "FIRST_NAME":"Evin", "LAST_NAME":"Byart", "AGE":19},
 {"ID":7, "FIRST_NAME":"Uri", "LAST_NAME":"Danielkiewicz", "AGE":21},
 {"ID":8, "FIRST_NAME":"Darell", "LAST_NAME":"De Ath", "AGE":34},
 {"ID":9, "FIRST_NAME":"Bab", "LAST_NAME":"Darcy", "AGE":46},
 {"ID":10, "FIRST_NAME":"Arin", "LAST_NAME":"Pethick", "AGE":59},
 {"ID":11, "FIRST_NAME":"Josh", "LAST_NAME":"Pridham", "AGE":26}]